visusat/__init__.py
visusat/copernicus.py
visusat/eumetsat.py
visusat/eumetsat_products_registry.py
visusat/utils.py
visusat-0.2.0.dist-info/licenses/LICENSE
visusat-0.2.0.dist-info/METADATA
visusat-0.2.0.dist-info/WHEEL
visusat-0.2.0.dist-info/top_level.txt
visusat-0.2.0.dist-info/RECORD
