Metadata-Version: 2.4
Name: visusat
Version: 0.2.0
Summary: Satellite data visualisation toolkit for EUMETSAT and Copernicus Marine datasets.
Author-email: Nicolas Sasso <n.sasso56@gmail.com>
License: MIT License
Project-URL: Homepage, https://github.com/nsasso56-cell/VisuSat
Project-URL: Documentation, https://visusat.readthedocs.io
Project-URL: Source, https://github.com/nsasso56-cell/VisuSat
Project-URL: Issues, https://github.com/nsasso56-cell/VisuSat/issues
Keywords: EUMETSAT,Copernicus,remote sensing,satellite,oceanography,meteorology,visualization,xarray
Classifier: Development Status :: 3 - Alpha
Classifier: Programming Language :: Python :: 3
Classifier: Programming Language :: Python :: 3.9
Classifier: License :: OSI Approved :: MIT License
Classifier: Operating System :: OS Independent
Classifier: Intended Audience :: Science/Research
Classifier: Topic :: Scientific/Engineering :: Atmospheric Science
Requires-Python: >=3.9
License-File: LICENSE
Requires-Dist: eumdac
Requires-Dist: xarray
Requires-Dist: matplotlib
Requires-Dist: pandas>=2.3.3
Requires-Dist: h5py>=3.14.0
Requires-Dist: netcdf4>=1.7.2
Requires-Dist: h5netcdf>=1.6.4
Requires-Dist: cdsapi>=0.7.7
Requires-Dist: copernicusmarine>=2.2.3
Requires-Dist: rioxarray>=0.15.0
Requires-Dist: sphinx>=7.4.7
Requires-Dist: sphinx-autodoc-typehints>=2.3.0
Requires-Dist: sphinx-rtd-theme>=3.0.2
Requires-Dist: myst-parser>=3.0.1
Requires-Dist: tree>=0.2.4
Dynamic: license-file
